torch_skeleton/__init__.py
torch_skeleton/utils.py
torch_skeleton/datasets/__init__.py
torch_skeleton/datasets/babel.py
torch_skeleton/datasets/base_dataset.py
torch_skeleton/datasets/dutils.py
torch_skeleton/datasets/ntu.py
torch_skeleton/datasets/ntu_graph_dataset.py
torch_skeleton/datasets/ntu_torch_dataset.py
torch_skeleton/datasets/ucla.py
torch_skeleton/transforms/__init__.py
torch_skeleton/transforms/functional.py
torch_skeleton/transforms/transforms.py
torch_skeleton-0.1.2.dist-info/LICENSE
torch_skeleton-0.1.2.dist-info/METADATA
torch_skeleton-0.1.2.dist-info/WHEEL
torch_skeleton-0.1.2.dist-info/top_level.txt
torch_skeleton-0.1.2.dist-info/RECORD
