Metadata-Version: 2.1
Name: torch-skeleton
Version: 0.1.2
Summary: skeleton datasets and transforms for pytorch
Author-email: Chanhyuk Jung <urw7rs@stu.kmu.ac.kr>
License: MIT License
Keywords: action,recognition,pytorch
Classifier: License :: OSI Approved :: MIT License
Classifier: Programming Language :: Python
Classifier: Programming Language :: Python :: 3
Requires-Python: >=3.8
License-File: LICENSE
Requires-Dist: numpy
Requires-Dist: torch
Requires-Dist: einops
Requires-Dist: scipy
Requires-Dist: gdown
Requires-Dist: wget
Provides-Extra: dev
Requires-Dist: black ; extra == 'dev'
Requires-Dist: pip-tools ; extra == 'dev'
Requires-Dist: pytest ; extra == 'dev'
Requires-Dist: pytest-cov ; extra == 'dev'
Requires-Dist: pytest-xdist ; extra == 'dev'
Requires-Dist: flake8 ; extra == 'dev'
Provides-Extra: doc
Requires-Dist: sphinx ; extra == 'doc'
Requires-Dist: sphinx-rtd-theme ; extra == 'doc'
Requires-Dist: myst-nb ; extra == 'doc'
Provides-Extra: examples
Requires-Dist: pytorch-lightning ; extra == 'examples'
Requires-Dist: fvcore ; extra == 'examples'
Requires-Dist: wandb ; extra == 'examples'
Requires-Dist: rich ; extra == 'examples'
Requires-Dist: torch-geometric ; extra == 'examples'
Requires-Dist: jsonargparse[signatures] (>=4.12.0) ; extra == 'examples'
Provides-Extra: testing
Requires-Dist: pytest (>=6.0) ; extra == 'testing'
Requires-Dist: pytest-cov (>=2.0) ; extra == 'testing'
Requires-Dist: flake8 (>=3.9) ; extra == 'testing'
Requires-Dist: tox (>=3.24) ; extra == 'testing'
Requires-Dist: black (>=21.9b0) ; extra == 'testing'
